ddlsplit/__init__.py
ddlsplit/__main__.py
ddlsplit-0.1.2.dist-info/entry_points.txt
ddlsplit-0.1.2.dist-info/LICENSE
ddlsplit-0.1.2.dist-info/WHEEL
ddlsplit-0.1.2.dist-info/METADATA
ddlsplit-0.1.2.dist-info/RECORD
