Metadata-Version: 2.1
Name: ddlsplit
Version: 0.1.2
Summary: Splits a DDL file generated by pgModeler by database objects into single DDL files.
Home-page: https://github.com/winkelband/ddlsplit/
License: GPL-3.0-or-later
Keywords: Database,SQL,Documentation
Author: David Berthel
Author-email: code@davidberthel.de
Requires-Python: >=3.6,<4.0
Classifier: License :: OSI Approved :: GNU General Public License v3 or later (GPLv3+)
Classifier: Programming Language :: Python :: 3
Classifier: Programming Language :: Python :: 3.6
Classifier: Programming Language :: Python :: 3.7
Classifier: Programming Language :: Python :: 3.8
Classifier: Programming Language :: Python :: 3.9
Project-URL: Repository, https://github.com/winkelband/ddlsplit/
